flake8_datetimez.py
test_datetimez.py
flake8_datetimez-20.10.0.dist-info/LICENSE
flake8_datetimez-20.10.0.dist-info/METADATA
flake8_datetimez-20.10.0.dist-info/WHEEL
flake8_datetimez-20.10.0.dist-info/entry_points.txt
flake8_datetimez-20.10.0.dist-info/top_level.txt
flake8_datetimez-20.10.0.dist-info/RECORD
