Metadata-Version: 2.1
Name: flake8-datetimez
Version: 20.10.0
Summary: A plugin for flake8 to ban the usage of unsafe naive datetime class.
Home-page: https://github.com/pjknkda/flake8-datetimez
Author: Jungkook Park
Author-email: jk@elicer.com
License: MIT
Keywords: flake8 datetime pyflakes pylint linter qa
Platform: UNKNOWN
Classifier: Development Status :: 5 - Production/Stable
Classifier: Environment :: Console
Classifier: Framework :: Flake8
Classifier: Intended Audience :: Developers
Classifier: License :: OSI Approved :: MIT License
Classifier: Operating System :: OS Independent
Classifier: Programming Language :: Python
Classifier: Programming Language :: Python :: 3
Classifier: Programming Language :: Python :: 3.6
Classifier: Programming Language :: Python :: 3.7
Classifier: Programming Language :: Python :: 3.9
Classifier: Programming Language :: Python :: 3 :: Only
Classifier: Topic :: Software Development :: Libraries :: Python Modules
Classifier: Topic :: Software Development :: Quality Assurance
Requires-Python: >=3.6
Requires-Dist: flake8 (>=3.0.0)
